<?xml version="1.0"?>
<XmlWorldData xmlns:xsi="http://www.w3.org/2001/XMLSchema-instance" xmlns:xsd="http://www.w3.org/2001/XMLSchema">
  <id>4b2d187a-c789-466c-a64d-b709e5441fd0</id>
  <name>Shadow Hunter v22</name>
  <description>&lt;ls&gt; move
&lt;rs&gt; shoot
&lt;x&gt; light
&lt;a&gt; grenade (costs hit points)

Find the coins. Keep the light out as much as possible.</description>
  <creator>mattmac</creator>
  <lastWriteTime>2009-06-27T19:05:01</lastWriteTime>
  <rating>1</rating>
  <challenge>false</challenge>
  <challengeID>0</challengeID>
  <stuffFilename>Xml\Levels\Stuff\4b2d187a-c789-466c-a64d-b709e5441fd0.Xml</stuffFilename>
  <preGame>Nothing</preGame>
  <dirty>false</dirty>
  <genres>2374</genres>
  <glassWalls>true</glassWalls>
  <showCompass>true</showCompass>
  <waveHeight>0.199999973</waveHeight>
  <waterStrength>0.2</waterStrength>
  <cameraSpringStrength>1</cameraSpringStrength>
  <fixedCamera>false</fixedCamera>
  <fixedCameraFrom>
    <X>3.506367</X>
    <Y>36.1858978</Y>
    <Z>12.7526026</Z>
  </fixedCameraFrom>
  <fixedCameraAt>
    <X>1.19697165</X>
    <Y>26.5061</Y>
    <Z>5.339237</Z>
  </fixedCameraAt>
  <fixedCameraDistance>12.4092617</fixedCameraDistance>
  <fixedCameraPitch>-0.6402623</fixedCameraPitch>
  <fixedCameraRotation>4.47818851</fixedCameraRotation>
  <fixedOffsetCamera>true</fixedOffsetCamera>
  <fixedOffset>
    <X>-1.96810174</X>
    <Y>11.2880249</Y>
    <Z>7.027241</Z>
  </fixedOffset>
  <editCameraAt>
    <X>3.767517</X>
    <Y>29.50665</Y>
    <Z>5.32397842</Z>
  </editCameraAt>
  <editCameraFrom>
    <X>3.00818634</X>
    <Y>48.65071</Y>
    <Z>13.163784</Z>
  </editCameraFrom>
  <editCameraRotation>4.75203228</editCameraRotation>
  <editCameraPitch>-0.388407528</editCameraPitch>
  <editCameraDistance>20.701067</editCameraDistance>
  <playCameraAt>
    <X>14.4112282</X>
    <Y>-17.0666943</Y>
    <Z>5.32398129</Z>
  </playCameraAt>
  <playCameraFrom>
    <X>12.4431267</X>
    <Y>-5.77866936</Y>
    <Z>12.351223</Z>
  </playCameraFrom>
  <playCameraValid>false</playCameraValid>
  <followCameraDistance>13.4415426</followCameraDistance>
  <followCameraValid>true</followCameraValid>
  <skyGradient>
    <Vector4>
      <X>0</X>
      <Y>0</Y>
      <Z>0</Z>
      <W>0</W>
    </Vector4>
    <Vector4>
      <X>0</X>
      <Y>0</Y>
      <Z>0</Z>
      <W>1</W>
    </Vector4>
    <Vector4>
      <X>0</X>
      <Y>0</Y>
      <Z>0</Z>
      <W>1</W>
    </Vector4>
    <Vector4>
      <X>0</X>
      <Y>0</Y>
      <Z>0</Z>
      <W>1</W>
    </Vector4>
    <Vector4>
      <X>0</X>
      <Y>0</Y>
      <Z>0</Z>
      <W>1</W>
    </Vector4>
  </skyGradient>
  <skyIndex>0</skyIndex>
  <lightRig>Really Dark</lightRig>
  <windMin>0</windMin>
  <windMax>0.5</windMax>
  <debugPathFollow>false</debugPathFollow>
  <debugDisplayCollisions>false</debugDisplayCollisions>
  <debugDisplayLinesOfPerception>false</debugDisplayLinesOfPerception>
  <uiVolume>1</uiVolume>
  <foleyVolume>1</foleyVolume>
  <musicVolume>1</musicVolume>
  <startingCamera>false</startingCamera>
  <startingCameraFrom>
    <X>0</X>
    <Y>0</Y>
    <Z>0</Z>
  </startingCameraFrom>
  <startingCameraAt>
    <X>0</X>
    <Y>0</Y>
    <Z>0</Z>
  </startingCameraAt>
  <startingCameraRotation>0</startingCameraRotation>
  <startingCameraPitch>0</startingCameraPitch>
  <startingCameraDistance>0</startingCameraDistance>
  <scoreSettings>
    <ScoreXmlSetting>
      <color>White</color>
      <visibility>Loud</visibility>
    </ScoreXmlSetting>
    <ScoreXmlSetting>
      <color>Black</color>
      <visibility>Loud</visibility>
    </ScoreXmlSetting>
    <ScoreXmlSetting>
      <color>Grey</color>
      <visibility>Loud</visibility>
    </ScoreXmlSetting>
    <ScoreXmlSetting>
      <color>Red</color>
      <visibility>Loud</visibility>
    </ScoreXmlSetting>
    <ScoreXmlSetting>
      <color>Green</color>
      <visibility>Loud</visibility>
    </ScoreXmlSetting>
    <ScoreXmlSetting>
      <color>Blue</color>
      <visibility>Loud</visibility>
    </ScoreXmlSetting>
    <ScoreXmlSetting>
      <color>Orange</color>
      <visibility>Loud</visibility>
    </ScoreXmlSetting>
    <ScoreXmlSetting>
      <color>Yellow</color>
      <visibility>Loud</visibility>
    </ScoreXmlSetting>
    <ScoreXmlSetting>
      <color>Purple</color>
      <visibility>Loud</visibility>
    </ScoreXmlSetting>
    <ScoreXmlSetting>
      <color>Pink</color>
      <visibility>Loud</visibility>
    </ScoreXmlSetting>
    <ScoreXmlSetting>
      <color>Brown</color>
      <visibility>Loud</visibility>
    </ScoreXmlSetting>
  </scoreSettings>
  <xmlTerrainData2>
    <virtualMapFile>Xml\Levels\Stuff\TerrainHeightMaps\b13f50bf-f981-4ac6-912b-6fbef4149657.Raw</virtualMapFile>
    <cubeSize>0.5</cubeSize>
    <waters />
  </xmlTerrainData2>
  <waterNormalMapTextureFilename>Textures\Terrain\WaterNormalMap</waterNormalMapTextureFilename>
  <creatableIds>201876d5-fe94-41da-bc86-e5221c0043e1</creatableIds>
  <creatableIds>0074ed08-d23d-4f5f-82a2-d9dfa1396307</creatableIds>
  <creatableIds>b36bdd1c-666b-4618-a23c-d37d20b082d5</creatableIds>
  <creatableIds>b59e5929-b402-4505-92b8-545253c70009</creatableIds>
  <creatableIds>df436cdd-09de-4310-a657-4714b63c47f8</creatableIds>
  <creatableIds>ab477b06-fd20-4be5-bd60-781534ca7955</creatableIds>
  <creatableIds>3e2b576f-19b4-445f-9519-aaa528672ad9</creatableIds>
</XmlWorldData>