<animation>
  <!-- FLOATBOT - Tobo -->

  <tickspersecond>30.0</tickspersecond>

  <animationsubset>
    <name>idle</name>
    <startframe>1</startframe>
    <endframe>50</endframe>
  </animationsubset>

  <animationsubset>
    <name>entertainment</name>
    <startframe>70</startframe>
    <endframe>87</endframe>
  </animationsubset>

  <animationsubset>
    <name>entertainment2</name>
    <startframe>90</startframe>
    <endframe>112</endframe>
  </animationsubset>

  <animationsubset>
    <name>entertainment3</name>
    <startframe>114</startframe>
    <endframe>265</endframe>
  </animationsubset>

  <animationsubset>
    <name>entertainment4</name>
    <startframe>266</startframe>
    <endframe>283</endframe>
  </animationsubset>

  <animationsubset>
    <name>entertainment5</name>
    <startframe>284</startframe>
    <endframe>534</endframe>
  </animationsubset>

  <animationsubset>
    <name>cursorreact</name>
    <startframe>51</startframe>
      <endframe>69</endframe>
    </animationsubset>

</animation>
